file_organizer/__init__.py
file_organizer/file_organizer.py
password_generator/__init__.py
password_generator/password_generator.py
weather_cli/__init__.py
weather_cli/weather_cli.py
python_cli_tools-0.2.5.dist-info/LICENSE
python_cli_tools-0.2.5.dist-info/METADATA
python_cli_tools-0.2.5.dist-info/WHEEL
python_cli_tools-0.2.5.dist-info/entry_points.txt
python_cli_tools-0.2.5.dist-info/top_level.txt
python_cli_tools-0.2.5.dist-info/RECORD
