Metadata-Version: 2.1
Name: python-cli-tools
Version: 0.2.5
Summary: A collection of practical Python CLI tools
Author: Łukasz Perek
License: MIT License
Project-URL: Homepage, https://github.com/wrogistefan/python-cli-tools
Project-URL: Repository, https://github.com/wrogistefan/python-cli-tools
Project-URL: Changelog, https://github.com/wrogistefan/python-cli-tools/blob/main/CHANGELOG.md
Keywords: cli,tools,utilities,command-line,python
Classifier: Programming Language :: Python :: 3
Classifier: Programming Language :: Python :: 3.10
Classifier: Programming Language :: Python :: 3.11
Classifier: Programming Language :: Python :: 3.12
Classifier: Operating System :: OS Independent
Classifier: Intended Audience :: Developers
Classifier: Topic :: Utilities
Requires-Python: >=3.10
License-File: LICENSE
Requires-Dist: requests>=2.31.0
